{"chunk_definitions":[{"chunk_id":"csetup_chunk","chunk_label":"setup","document_id":"E9CEEF96","expansion_state":0,"options":{"engine":"r","include":false,"label":"setup"},"row":8,"row_count":1,"visible":true},{"chunk_id":"c1o1pe50gweya","chunk_label":"unnamed-chunk-4","document_id":"E9CEEF96","expansion_state":0,"options":{"engine":"r","label":"unnamed-chunk-16"},"row":37,"row_count":1,"visible":true},{"chunk_id":"cri8vjiwwfqoj","chunk_label":"unnamed-chunk-7","document_id":"E9CEEF96","expansion_state":0,"options":{"engine":"r","label":"unnamed-chunk-17"},"row":56,"row_count":1,"visible":true}],"default_chunk_options":{"error":false},"doc_write_time":1540546570,"working_dir":null}